prefect_fivetran/__init__.py
prefect_fivetran/_version.py
prefect_fivetran/clients.py
prefect_fivetran/connectors.py
prefect_fivetran/credentials.py
prefect_fivetran-0.1.0b0.dist-info/LICENSE
prefect_fivetran-0.1.0b0.dist-info/METADATA
prefect_fivetran-0.1.0b0.dist-info/WHEEL
prefect_fivetran-0.1.0b0.dist-info/entry_points.txt
prefect_fivetran-0.1.0b0.dist-info/top_level.txt
prefect_fivetran-0.1.0b0.dist-info/RECORD
